cao_lang/cao_lang_py.abi3.so
cao_lang/__init__.py
cao_lang-0.2.5.dist-info/RECORD
cao_lang-0.2.5.dist-info/WHEEL
cao_lang-0.2.5.dist-info/LICENSE
cao_lang-0.2.5.dist-info/top_level.txt
cao_lang-0.2.5.dist-info/METADATA
