Metadata-Version: 2.1
Name: cao-lang
Version: 0.2.5
Summary: The node based 'language' that governs the actors of the game Cao-Lo
Home-page: https://github.com/caolo-game/cao-lang
Author: Daniel Kiss
Author-email: littlesnorrboy@gmail.com
Project-URL: Bug Tracker, https://github.com/caolo-game/cao-lang/issues
Classifier: Programming Language :: Python :: 3
Classifier: License :: OSI Approved :: MIT License
Classifier: Development Status :: 2 - Pre-Alpha
Classifier: Programming Language :: Python :: 3 :: Only
Classifier: Programming Language :: Rust
License-File: LICENSE
